PEMtest/__init__.py
PEMtest/pem.py
pemtest-0.0.2.dist-info/LICENSE
pemtest-0.0.2.dist-info/METADATA
pemtest-0.0.2.dist-info/WHEEL
pemtest-0.0.2.dist-info/top_level.txt
pemtest-0.0.2.dist-info/RECORD
