Metadata-Version: 2.1
Name: pemtest
Version: 0.0.2
Summary: "Parameters Elimination Method" Goodness-Of-Fit test for normality
Home-page: https://github.com/turkunov/pem-test
Author: Turkunov
Author-email: yaturkunov@gmail.com
Classifier: Programming Language :: Python :: 3
Classifier: License :: OSI Approved :: MIT License
Classifier: Operating System :: OS Independent
Requires-Python: >=3.6
License-File: LICENSE
